{
    "editor.minimap.enabled": false,
    "editor.fontSize": 10.5,
    "editor.fontWeight": "100",
    "window.zoomLevel": 1,
    "files.autoSave": "afterDelay",
    "zenMode.fullScreen": false,
    "json.schemas": [],
    "window.commandCenter": false,
    "terminal.integrated.fontSize": 11,
    "terminal.integrated.fontFamily": "Consolas",
    "editor.fontLigatures": true,
    "editor.tokenColorCustomizations": {
    "textMateRules": [
    {
      "scope": [
        "comment",
        "comment.line",
        "comment.block.documentation"
      ],
      "settings": {
        "fontStyle": "italic"
          }
        }
      ]
    },
    "editor.codeActionsOnSave": {},
    "diffEditor.hideUnchangedRegions.enabled": true,
    "editor.stickyScroll.enabled": false,
    "explorer.confirmDragAndDrop": false,
    "explorer.confirmDelete": false,
    "terminal.integrated.fontLigatures.enabled": true,
    "vscode_custom_css.imports": [
      "file:///C:/Users/Maxwell%20Easter/OneDrive/Desktop/Bin/Github/others/config/custom.css"
    ],
    "workbench.settings.applyToAllProfiles": [
    ],
    "extensions.experimental.affinity": {
      "asvetliakov.vscode-neovim": 1
    },
    "editor.overtypeCursorStyle": "line",
    "editor.cursorBlinking": "smooth",
    "markdown.preview.fontSize": 9,
    "markdown-preview-enhanced.previewTheme": "atom-dark.css",
    "editor.fontFamily": "'Nimbus Mono'",
    "workbench.secondarySideBar.defaultVisibility": "hidden",
    "workbench.statusBar.visible": false,
    "workbench.startupEditor": "none",
    "workbench.iconTheme": "material-icon-theme",
    "terminal.integrated.stickyScroll.enabled": false,
    "breadcrumbs.enabled": false,
    "terminal.integrated.enableMultiLinePasteWarning": "never",
    "workbench.colorTheme": "Best Themes - One Dark Pro"
}

